dramatiq_pg/__init__.py
dramatiq_pg/broker.py
dramatiq_pg/cli.py
dramatiq_pg/results.py
dramatiq_pg/schema.py
dramatiq_pg/schema.sql
dramatiq_pg/utils.py
dramatiq_pg-0.12.0.dist-info/entry_points.txt
dramatiq_pg-0.12.0.dist-info/LICENSE
dramatiq_pg-0.12.0.dist-info/METADATA
dramatiq_pg-0.12.0.dist-info/WHEEL
dramatiq_pg-0.12.0.dist-info/RECORD
