Metadata-Version: 2.1
Name: dramatiq-pg
Version: 0.12.0
Summary: Postgres Broker for Dramatiq Task Queue
Home-page: https://gitlab.com/dalibo/dramatiq-pg
License: PostgreSQL
Keywords: postgres,task queue,dramatiq
Author: Étienne BERSAC
Requires-Python: >=3.6,<4.0
Classifier: License :: OSI Approved
Classifier: Programming Language :: Python :: 3
Classifier: Programming Language :: Python :: 3.6
Classifier: Programming Language :: Python :: 3.7
Classifier: Programming Language :: Python :: 3.8
Classifier: Programming Language :: Python :: 3.9
Classifier: Programming Language :: Python :: 3.10
Classifier: Programming Language :: Python :: 3.11
Requires-Dist: dramatiq (>=1.5,<2.0)
Requires-Dist: tenacity (>=8,<9)
Project-URL: Documentation, https://gitlab.com/dalibo/dramatiq-pg/blob/master/docs/index.rst
